LICENSE.txt
MANIFEST.in
README.md
pyproject.toml
setup.cfg
src/py_dual_sorter/build_info.py
src/py_dual_sorter/constants_version.py
src/py_dual_sorter/py_dual_sorter.py
src/py_dual_sorter.egg-info/PKG-INFO
src/py_dual_sorter.egg-info/SOURCES.txt
src/py_dual_sorter.egg-info/dependency_links.txt
src/py_dual_sorter.egg-info/requires.txt
src/py_dual_sorter.egg-info/top_level.txt