Metadata-Version: 2.4
Name: py-dual-sorter
Version: 0.1.1
Summary: Sort content by two keys
Author-email: "J. Arrizza" <cppgent0@gmail.com>
Maintainer-email: "J. Arrizza" <cppgent0@gmail.com>
License-Expression: MIT
Project-URL: Website, https://arrizza.com/py-dual-sorter
Project-URL: Source, https://bitbucket.org/arrizza-public/py-dual-sorter/src/master
Project-URL: Download, https://bitbucket.org/arrizza-public/py-dual-sorter/get/master.zip
Keywords: iteration,utilities
Classifier: Development Status :: 4 - Beta
Classifier: Environment :: Console
Classifier: Topic :: Utilities
Classifier: Intended Audience :: Developers
Classifier: Programming Language :: Python :: 3.10
Classifier: Programming Language :: Python :: 3.12
Requires-Python: >=3.9
License-File: LICENSE.txt
Requires-Dist: falcon-logger
Dynamic: license-file
